av2bv/__init__.py
av2bv/av2bv.py
av2bv-0.1.2.dist-info/METADATA
av2bv-0.1.2.dist-info/WHEEL
av2bv-0.1.2.dist-info/top_level.txt
av2bv-0.1.2.dist-info/RECORD
