Metadata-Version: 2.1
Name: av2bv
Version: 0.1.2
Summary: Bilibili av⇔BV
Home-page: https://github.com/liziyi0914/av2bv-py
Author: liziyi0914
Author-email: liziyi0914@gmail.com
License: MIT License
Platform: all
